prism_models/__init__.py
prism_models/agent_profile.py
prism_models/base.py
prism_models/chat.py
prism_models/config.py
prism_models/content.py
prism_models/feedback.py
prism_models/qdrant.py
prism_models/migration/README
prism_models/migration/__init__.py
prism_models/migration/env.py
prism_models/migration/script.py.mako
prism_models/migration/versions/2025_09_11_1516_161f8829d93f_initial_schema.py
prism_models/migration/versions/2025_09_11_1558_5e011849ea76_changes_for_feedback.py
prism_models/migration/versions/2025_09_14_2243_059af231c2b2_profile_entities.py
prism_models/migration/versions/2025_09_15_1646_3219fec0bb10_agent_changes.py
prism_models/migration/versions/2025_09_16_1627_f2013b08daac_rename_metadata_to_additional_data.py
prism_models/migration/versions/2025_09_17_1147_327febbf555f_display_name_added.py
prism_models/migration/versions/2025_09_18_1106_b0bcb7ca1dc9_add_support_for_profile_on_create_convo.py
prism_models/migration/versions/2025_09_18_1511_bbc1955191e6_preview_mode.py
prism_models/migration/versions/2025_09_26_1115_6eb70e848451_added_publish_status_to_document.py
prism_models/migration/versions/2025_09_26_1240_f8b0ea2e743c_drop_unique_title_version_on_document.py
prism_models/migration/versions/2025_09_26_1505_07dc8c2589e0_added_chunk_id_and_vector_embeddings_to_.py
prism_models/migration/versions/2025_09_29_1220_46ba2693b883_add_markdown_markdown_file_path_s3_.py
prism_models/migration/versions/2025_10_02_1520_bf1472a9b021_removed_doc_id_from_config_table_and_.py
prism_models/migration/versions/2025_10_02_1525_6c0e63e0fef8_removed_doc_id_from_config_table_.py
prism_models/migration/versions/2025_10_02_1608_1b3eb48f5017_config_id_on_delete_will_be_set_to_null.py
prism_models/migration/versions/2025_10_03_1109_ac85b606d8a4_added_docling_hybrid_to_chunkstrategy.py
prism_models/migration/versions/2025_10_03_1204_7d1cb343a63f_added_s3_bucket_and_s3_dir_in_source_.py
prism_models-0.6.5.dist-info/METADATA
prism_models-0.6.5.dist-info/WHEEL
prism_models-0.6.5.dist-info/top_level.txt
prism_models-0.6.5.dist-info/RECORD
