Metadata-Version: 2.4
Name: prism-models
Version: 0.6.5
Requires-Python: >=3.12
Requires-Dist: sqlalchemy[asyncio]>=2.0.0
Requires-Dist: alembic>=1.16.0
Requires-Dist: asyncpg>=0.29.0
Requires-Dist: pydantic>=2.0.0
Requires-Dist: pydantic-settings>=2.1.0
Requires-Dist: uuid7>=0.1.0
